{
    "urls": {
        "F3": "F3.[mp3|ogg]",
        "F#1": "Fs1.[mp3|ogg]",
        "F#2": "Fs2.[mp3|ogg]",
        "F#3": "Fs3.[mp3|ogg]",
        "G1": "G1.[mp3|ogg]",
        "G2": "G2.[mp3|ogg]",
        "G3": "G3.[mp3|ogg]",
        "G#1": "Gs1.[mp3|ogg]",
        "G#2": "Gs2.[mp3|ogg]",
        "G#3": "Gs3.[mp3|ogg]",
        "A1": "A1.[mp3|ogg]",
        "A2": "A2.[mp3|ogg]",
        "A3": "A3.[mp3|ogg]",
        "A#1": "As1.[mp3|ogg]",
        "A#2": "As2.[mp3|ogg]",
        "A#3": "As3.[mp3|ogg]",
        "B1": "B1.[mp3|ogg]",
        "B2": "B2.[mp3|ogg]",
        "B3": "B3.[mp3|ogg]",
        "C2": "C2.[mp3|ogg]",
        "C3": "C3.[mp3|ogg]",
        "C4": "C4.[mp3|ogg]",
        "C#2": "Cs2.[mp3|ogg]",
        "C#3": "Cs3.[mp3|ogg]",
        "C#4": "Cs4.[mp3|ogg]",
        "D1": "D1.[mp3|ogg]",
        "D2": "D2.[mp3|ogg]",
        "D3": "D3.[mp3|ogg]",
        "D4": "D4.[mp3|ogg]",
        "D#1": "Ds1.[mp3|ogg]",
        "D#2": "Ds2.[mp3|ogg]",
        "D#3": "Ds3.[mp3|ogg]",
        "E1": "E1.[mp3|ogg]",
        "E2": "E2.[mp3|ogg]",
        "E3": "E3.[mp3|ogg]",
        "F1": "F1.[mp3|ogg]",
        "F2": "F2.[mp3|ogg]"
    },
    "baseUrl": "/assets/samples/guitar-accoustic/"
}